{
  "$type": "Bespoke.Ost.PosLajuBranchBranches.Domain.PosLajuBranch, Ost.PosLajuBranch",
  "BranchCode": "4300",
  "Name": "Kajang",
  "PostcodeFrom": "43500",
  "PostcodeTo": "43599",
  "Email": "KPPoslajuBBBangi@pos.com.my",
  "PickupId": "289",
  "AllowPickup": true,
  "CreatedBy": "admin",
  "Id": "289",
  "CreatedDate": "2017-07-18T14:22:01.853429+08:00",
  "ChangedBy": "admin",
  "ChangedDate": "2017-07-18T14:22:02.915474+08:00",
  "WebId": "c6857eaa-be00-4439-b16a-71388985f003"
}