{
  "$type": "Bespoke.Ost.PosLajuBranchBranches.Domain.PosLajuBranch, Ost.PosLajuBranch",
  "BranchCode": "8700",
  "Name": "Labuan",
  "PostcodeFrom": "87000",
  "PostcodeTo": "87000",
  "Email": "KPPoslajuLabuan@pos.com.my",
  "PickupId": "357",
  "AllowPickup": true,
  "CreatedBy": "admin",
  "Id": "357",
  "CreatedDate": "2016-11-03T10:52:04.6804331+08:00",
  "ChangedBy": "admin",
  "ChangedDate": "2017-08-16T13:28:44.4300499+08:00",
  "WebId": "a3039143-25f4-4e3b-8124-1712331b2c11"
}