{
  "$type": "Bespoke.Sph.Domain.OperationEndpoint, domain.sph",
  "EntityPermissionCollection": {
    "$type": "Bespoke.Sph.Domain.ObjectCollection`1[[Bespoke.Sph.Domain.EntityPermission, domain.sph]], domain.sph",
    "$values": []
  },
  "Rules": {
    "$type": "Bespoke.Sph.Domain.ObjectCollection`1[[System.String, mscorlib]], domain.sph",
    "$values": []
  },
  "SetterActionChildCollection": {
    "$type": "Bespoke.Sph.Domain.ObjectCollection`1[[Bespoke.Sph.Domain.SetterActionChild, domain.sph]], domain.sph",
    "$values": []
  },
  "PatchPathCollection": {
    "$type": "Bespoke.Sph.Domain.ObjectCollection`1[[Bespoke.Sph.Domain.PatchSetter, domain.sph]], domain.sph",
    "$values": []
  },
  "ReferencedAssemblyCollection": {
    "$type": "Bespoke.Sph.Domain.ObjectCollection`1[[Bespoke.Sph.Domain.ReferencedAssembly, domain.sph]], domain.sph",
    "$values": []
  },
  "Name": "DefaultOrder",
  "Route": "",
  "IsHttpPut": true,
  "IsHttpPatch": false,
  "IsHttpPost": true,
  "IsHttpDelete": true,
  "Note": "",
  "Entity": "Order",
  "Resource": "orders",
  "IsPublished": true,
  "IsConflictDetectionEnabled": false,
  "CreatedBy": "admin",
  "Id": "order-default-order",
  "CreatedDate": "2016-10-17T17:12:21.0388258+08:00",
  "ChangedBy": "admin",
  "ChangedDate": "2016-10-17T17:16:50.7362517+08:00",
  "WebId": "c5133107-184f-401e-de93-62a2d0adb696"
}